xiang/__init__.py
xiang/cli.py
xiang/converter.py
xtof-1.0.1.dist-info/COPYING
xtof-1.0.1.dist-info/LICENSE
xtof-1.0.1.dist-info/METADATA
xtof-1.0.1.dist-info/WHEEL
xtof-1.0.1.dist-info/entry_points.txt
xtof-1.0.1.dist-info/top_level.txt
xtof-1.0.1.dist-info/RECORD
